brighthive_authlib/__init__.py
brighthive_authlib/config/__init__.py
brighthive_authlib/config/config.py
brighthive_authlib/decorators/__init__.py
brighthive_authlib/decorators/token_required_decorator.py
brighthive_authlib/providers/__init__.py
brighthive_authlib/providers/auth_zero_provider.py
brighthive_authlib/providers/provider.py
brighthive_authlib/providers/provider_error.py
brighthive_authlib/providers/provider_factory.py
examples/__init__.py
examples/example.py
tests/__init__.py
tests/conftest.py
tests/test_provider_factory.py
brighthive_authlib-1.0.4.dist-info/LICENSE
brighthive_authlib-1.0.4.dist-info/METADATA
brighthive_authlib-1.0.4.dist-info/WHEEL
brighthive_authlib-1.0.4.dist-info/top_level.txt
brighthive_authlib-1.0.4.dist-info/RECORD
