Metadata-Version: 2.1
Name: brighthive-authlib
Version: 1.0.4
Summary: BrightHive API Authorization and Authentication Library
Home-page: https://github.com/brighthive/authlib
Author: Gregory Mundy
Author-email: greg@brighthive.io
License: UNKNOWN
Platform: UNKNOWN
Classifier: Programming Language :: Python :: 3
Classifier: License :: OSI Approved :: MIT License
Classifier: Operating System :: OS Independent
Requires-Dist: flask
Requires-Dist: pycryptodome
Requires-Dist: python-jose[pycryptodome]
Requires-Dist: requests
